MANIFEST.in
README.txt
setup.py
docs/HISTORY.txt
docs/INSTALL.txt
docs/LICENSE.GPL
docs/LICENSE.txt
quintagroup/__init__.py
quintagroup.ploneformgen.readonlystringfield.egg-info/PKG-INFO
quintagroup.ploneformgen.readonlystringfield.egg-info/SOURCES.txt
quintagroup.ploneformgen.readonlystringfield.egg-info/dependency_links.txt
quintagroup.ploneformgen.readonlystringfield.egg-info/entry_points.txt
quintagroup.ploneformgen.readonlystringfield.egg-info/namespace_packages.txt
quintagroup.ploneformgen.readonlystringfield.egg-info/not-zip-safe
quintagroup.ploneformgen.readonlystringfield.egg-info/requires.txt
quintagroup.ploneformgen.readonlystringfield.egg-info/top_level.txt
quintagroup/ploneformgen/__init__.py
quintagroup/ploneformgen/readonlystringfield/__init__.py
quintagroup/ploneformgen/readonlystringfield/config.py
quintagroup/ploneformgen/readonlystringfield/configure.zcml
quintagroup/ploneformgen/readonlystringfield/field.py
quintagroup/ploneformgen/readonlystringfield/setuphandlers.py
quintagroup/ploneformgen/readonlystringfield/widget.py
quintagroup/ploneformgen/readonlystringfield/Extensions/Install.py
quintagroup/ploneformgen/readonlystringfield/Extensions/__init__.py
quintagroup/ploneformgen/readonlystringfield/profiles/default/factorytool.xml
quintagroup/ploneformgen/readonlystringfield/profiles/default/metadata.xml
quintagroup/ploneformgen/readonlystringfield/profiles/default/propertiestool.xml
quintagroup/ploneformgen/readonlystringfield/profiles/default/skins.xml
quintagroup/ploneformgen/readonlystringfield/profiles/default/types.xml
quintagroup/ploneformgen/readonlystringfield/profiles/default/workflows.xml
quintagroup/ploneformgen/readonlystringfield/profiles/default/types/FormFolder.xml
quintagroup/ploneformgen/readonlystringfield/profiles/default/types/FormReadonlyStringField.xml
quintagroup/ploneformgen/readonlystringfield/profiles/uninstall/import_steps.xml
quintagroup/ploneformgen/readonlystringfield/profiles/uninstall/propertiestool.xml
quintagroup/ploneformgen/readonlystringfield/profiles/uninstall/quintagroup.ploneformgen.readonlystringfield_uninstall.txt
quintagroup/ploneformgen/readonlystringfield/profiles/uninstall/skins.xml
quintagroup/ploneformgen/readonlystringfield/skins/readonlystringfield/readonlystring.pt
quintagroup/ploneformgen/readonlystringfield/tests/__init__.py
quintagroup/ploneformgen/readonlystringfield/tests/base.py
quintagroup/ploneformgen/readonlystringfield/tests/readonlystringfield.txt
quintagroup/ploneformgen/readonlystringfield/tests/test_docs.py
