Metadata-Version: 1.0
Name: quintagroup.ploneformgen.readonlystringfield
Version: 0.2
Summary: Readonly String Field for PloneFormGen product
Home-page: http://quintagroup.com/services/plone-development/products/
Author: Vitaliy Podoba
Author-email: piv@quintagroup.com
License: GPL
Keywords: plone form generator readonly field
Platform: UNKNOWN
Classifier: Framework :: Plone
Classifier: Programming Language :: Python
Classifier: Topic :: Software Development :: Libraries :: Python Modules
